nb2/__init__.py
nb2/_nbdev.py
nb2/core.py
nb2-0.0.2.dist-info/LICENSE
nb2-0.0.2.dist-info/METADATA
nb2-0.0.2.dist-info/WHEEL
nb2-0.0.2.dist-info/entry_points.txt
nb2-0.0.2.dist-info/top_level.txt
nb2-0.0.2.dist-info/RECORD
